topsis/Distance_Between_Ideal_and_Alternatives.py
topsis/Ideal_Solution.py
topsis/Normalization.py
topsis/Normalized_Decision_Matrix.py
topsis/Weighted_Normalized_Decision_Matrix.py
topsis/__init__.py
topsis/main.py
topsis/test_topsis.py
topsis_python_hamedbaziyad-0.0.1.dist-info/licenses/LICENSE
topsis_python_hamedbaziyad-0.0.1.dist-info/METADATA
topsis_python_hamedbaziyad-0.0.1.dist-info/WHEEL
topsis_python_hamedbaziyad-0.0.1.dist-info/top_level.txt
topsis_python_hamedbaziyad-0.0.1.dist-info/RECORD
