Metadata-Version: 2.4
Name: topsis-python-hamedbaziyad
Version: 0.0.1
Summary: Technique for Order of Preference by Similarity to Ideal Solution (TOPSIS) CHING-LAI Hwang and Yoon introduced TOPSIS in 1981 in their Multiple Criteria Decision Making (MCDM) and Multiple Criteria Decision Analysis (MCDA) methods
Author: Hamed Baziyad
Author-email: Lucas Piccioni Costa <lucascosta74@gmail.com>
License: MIT License
Project-URL: Homepage, https://github.com/pypa/sampleproject
Project-URL: Bug Tracker, https://github.com/pypa/sampleproject/issues
Classifier: Programming Language :: Python :: 3
Classifier: Operating System :: OS Independent
Requires-Python: >=3.7
License-File: LICENSE
Requires-Dist: pandas
Requires-Dist: numpy
Requires-Dist: openpyxl
Dynamic: license-file
